Metadata-Version: 2.1
Name: sudokumaker
Version: 1.2
Summary: Genetic-Algorithm based Sudoku generator (and solver)
Home-page: https://github.com/schlatterbeck/sudokumaker
Author: Ralf Schlatterbeck
Author-email: rsc@runtux.com
License: GNU General Public License (GPL)
Platform: Any
Classifier: Development Status :: 5 - Production/Stable
Classifier: Environment :: Console
Classifier: Intended Audience :: Developers
Classifier: Intended Audience :: Education
Classifier: Intended Audience :: End Users/Desktop
Classifier: License :: OSI Approved :: GNU General Public License (GPL)
Classifier: Operating System :: OS Independent
Classifier: Programming Language :: Python
Classifier: Topic :: Education
Classifier: Topic :: Games/Entertainment :: Puzzle Games
